CHANGELOG.rst
MANIFEST.in
MIT-LICENSE.txt
README.rst
requirements.txt
setup.py
test_requirements.txt
django_nvd3/__init__.py
django_nvd3.egg-info/PKG-INFO
django_nvd3.egg-info/SOURCES.txt
django_nvd3.egg-info/dependency_links.txt
django_nvd3.egg-info/not-zip-safe
django_nvd3.egg-info/requires.txt
django_nvd3.egg-info/top_level.txt
django_nvd3/templatetags/__init__.py
django_nvd3/templatetags/nvd3_tags.py